{
  "personalIdentification": {
    "fullName": "Monroe H. Postman"
  },
  "contactInformation": {
    "residentialAddress": "3939 Fabian Way, Palo Alto, California 94303",
    "phoneNumbers": "326-4350",
    "geographicLocation": "Palo Alto, California"
  },
  "professionalAffiliation": {
    "employerOrganization": "Philco Ford",
    "departmentDivision": "Western Development Laboratories"
  },
  "professionalIdentityExpertise": {
    "jobTitleOccupation": "Electronic engineer",
    "technicalFields": [
      "Electronics"
    ]
  }
}