{
  "personalIdentification": {
    "fullName": "Richard H Penney"
  },
  "contactInformation": {
    "residentialAddress": "405 East 56th Street, New York, New York 10022",
    "phoneNumbers": "861-7501",
    "geographicLocation": "New York, New York"
  },
  "professionalAffiliation": {
    "employerOrganization": "Henry Dreyfuss and Associates"
  },
  "professionalIdentityExpertise": {
    "jobTitleOccupation": "Freelancer",
    "technicalFields": [
      "industrial design",
      "product design",
      "graphic design",
      "architectural design"
    ],
    "specializedSkillsKnowledge": "industrial design, product, graphic, and architectural design"
  }
}