{
  "personalIdentification": {
    "fullName": "John E. Canepari"
  },
  "contactInformation": {
    "residentialAddress": "Governors Island, New York, New York 10004",
    "phoneNumbers": "(212) 264-4903",
    "geographicLocation": "Governors Island, New York, New York"
  },
  "professionalAffiliation": {
    "employerOrganization": "United States Coast Guard",
    "departmentDivision": "Civil Engineering Branch"
  },
  "professionalIdentityExpertise": {
    "jobTitleOccupation": "Civil Engineer",
    "technicalFields": [
      "civil engineering",
      "structural engineering",
      "hydraulics"
    ],
    "specializedSkillsKnowledge": "structural engineering, hydraulics"
  },
  "interestsCreativeActivities": {
    "artisticPursuits": "None specified",
    "aestheticPhilosophicalInterests": "None specified"
  }
}