{
  "personalIdentification": {
    "fullName": "Ed Conroy"
  },
  "contactInformation": {
    "residentialAddress": "4 Ambassador Lane, Selden, New York",
    "phoneNumbers": "Se 2-8825",
    "geographicLocation": "Selden, New York"
  },
  "professionalAffiliation": {
    "employerOrganization": "Grumman Aircraft"
  },
  "professionalIdentityExpertise": {
    "jobTitleOccupation": "Engineer",
    "technicalFields": [
      "data processing",
      "instrumentation"
    ],
    "specializedSkillsKnowledge": "data processing, instrumentation"
  }
}