{
  "entries": [
    {
      "name": "Otto Tambellini Jan?",
      "name_other": "null",
      "contact_method": "phone",
      "date": "null",
      "other_metadata": "null",
      "bounding_box": {
        "x1": 20.3,
        "y1": 8.4,
        "x2": 51.6,
        "y2": 17.5
      }
    },
    {
      "name": "Dolores Schapiro",
      "name_other": "null",
      "contact_method": "null",
      "date": "1970-11-11",
      "other_metadata": "null",
      "bounding_box": {
        "x1": 5.9,
        "y1": 17.9,
        "x2": 29.7,
        "y2": 29.4
      }
    }
  ]
}